phttp/__init__.py
phttp/__main__.py
phttps/__init__.py
phttps/__main__.py
pserve-0.1.1.dist-info/licenses/LICENSE
server/__init__.py
server/__main__.py
server/core.py
pserve-0.1.1.dist-info/METADATA
pserve-0.1.1.dist-info/WHEEL
pserve-0.1.1.dist-info/entry_points.txt
pserve-0.1.1.dist-info/top_level.txt
pserve-0.1.1.dist-info/RECORD
